viewer.py
misc/interface.py
ProtViewer-0.0.6.dist-info/LICENSE
ProtViewer-0.0.6.dist-info/METADATA
ProtViewer-0.0.6.dist-info/WHEEL
ProtViewer-0.0.6.dist-info/top_level.txt
ProtViewer-0.0.6.dist-info/RECORD
