Metadata-Version: 2.1
Name: ProtViewer
Version: 0.0.6
Summary: A web-based tool to visualize activities in proteins
Home-page: https://github.com/Old-Shatterhand/ProtViewer
Author: Roman Joeres
Author-email: romanjoeres@gmail.com
License: MIT
Keywords: python,visualization,protein,activity
Platform: any
Classifier: Development Status :: 3 - Alpha
Classifier: Environment :: Web Environment
Classifier: Intended Audience :: Education
Classifier: Intended Audience :: Healthcare Industry
Classifier: Intended Audience :: Science/Research
Classifier: License :: OSI Approved :: MIT License
Classifier: Operating System :: OS Independent
Classifier: Programming Language :: Python
Classifier: Programming Language :: Python :: 3
Classifier: Topic :: Education
Classifier: Topic :: Scientific/Engineering :: Bio-Informatics
Classifier: Topic :: Scientific/Engineering :: Information Analysis
Classifier: Topic :: Scientific/Engineering :: Visualization
Requires-Python: >=3.0
License-File: LICENSE
